Metadata-Version: 2.1
Name: ccwrapper
Version: 1.0.0
Summary: ccwrapper - это python модуль для упрощённой работы с CatCoin API
Home-page: https://github.com/duzive/ccwrapper
Author: Duzive
Author-email: duzive30@gmail.com
License: Apache License, Version 2.0, see LICENSE file
Download-URL: https://github.com/duzive/ccwrapper/archive/v1.0.0.zip
Platform: UNKNOWN
Classifier: License :: OSI Approved :: Apache Software License
Classifier: Operating System :: OS Independent
Classifier: Programming Language :: Python
Classifier: Programming Language :: Python :: 3.6
Classifier: Programming Language :: Python :: 3.7
Classifier: Programming Language :: Python :: 3.8
Classifier: Programming Language :: Python :: Implementation :: PyPy
Classifier: Programming Language :: Python :: Implementation :: CPython
